tc_core/__init__.py
tc_core/app.py
tc_core/context.py
tc_core/context_importer.py
tc_core/importer.py
tc_core/web.py
tc_core-0.4.1.dist-info/METADATA
tc_core-0.4.1.dist-info/RECORD
tc_core-0.4.1.dist-info/WHEEL
tc_core-0.4.1.dist-info/top_level.txt
