Metadata-Version: 2.1
Name: tc-core
Version: 0.4.1
Summary: Thumbor community extensions core
Home-page: http://github.com/thumbor_community/core
Author: Thumbor Community
License: MIT
Platform: any
Classifier: Development Status :: 4 - Beta
Classifier: Intended Audience :: Developers
Classifier: License :: OSI Approved :: MIT License
Classifier: Operating System :: OS Independent
Classifier: Programming Language :: Python
Classifier: Topic :: Software Development :: Libraries :: Python Modules
Provides-Extra: tests
Requires-Dist: libthumbor (>=1.3.0)
Requires-Dist: thumbor (>=5.0)
Provides-Extra: tests
Requires-Dist: pyvows; extra == 'tests'
Requires-Dist: coverage; extra == 'tests'
